keras_applications_3d/__init__.py
keras_applications_3d/_keras_backend_tensorflow_backend.py
keras_applications_3d/_keras_legacy_interfaces.py
keras_applications_3d/custom_layers.py
keras_applications_3d/densenet.py
keras_applications_3d/efficientnet.py
keras_applications_3d/imagenet_utils.py
keras_applications_3d/inception_resnet_v2.py
keras_applications_3d/inception_v3.py
keras_applications_3d/mobilenet.py
keras_applications_3d/mobilenet_v2.py
keras_applications_3d/mobilenet_v3.py
keras_applications_3d/nasnet.py
keras_applications_3d/resnet.py
keras_applications_3d/resnet_v2.py
keras_applications_3d/vgg16.py
keras_applications_3d/vgg19.py
keras_applications_3d/xception.py
Keras_Applications_3D-0.1.2.dist-info/LICENSE
Keras_Applications_3D-0.1.2.dist-info/METADATA
Keras_Applications_3D-0.1.2.dist-info/WHEEL
Keras_Applications_3D-0.1.2.dist-info/top_level.txt
Keras_Applications_3D-0.1.2.dist-info/RECORD
